{
  "id": "cricket-basics-lesson-1",
  "title": "History and Origins of Cricket",
  "description": "Discover the fascinating history of cricket from its origins in 16th century England to becoming a global phenomenon. Learn about the evolution of rules and formats.",
  "sourceApp": "learn-cricket",
  "module_id": "cricket-basics-module-1",
  "course_id": "cricket-basics",
  "order": 1,
  "duration": "30 minutes",
  "content": "Cricket has a rich history dating back to the 16th century in England..."
}
